AUTHORS.rst
CONTRIBUTING.rst
HISTORY.rst
LICENSE
MANIFEST.in
README.rst
setup.cfg
setup.py
docs/Makefile
docs/authors.rst
docs/conf.py
docs/contributing.rst
docs/history.rst
docs/idpflex.rst
docs/index.rst
docs/installation.rst
docs/make.bat
docs/usage.rst
docs/_build/html/_images/data_download_ascii_file.png
docs/_build/html/_images/data_download_file.png
docs/_build/html/_images/data_download_zip.png
docs/_build/html/_images/with_python.png
docs/_build/html/_static/ajax-loader.gif
docs/_build/html/_static/comment-bright.png
docs/_build/html/_static/comment-close.png
docs/_build/html/_static/comment.png
docs/_build/html/_static/down-pressed.png
docs/_build/html/_static/down.png
docs/_build/html/_static/file.png
docs/_build/html/_static/minus.png
docs/_build/html/_static/plus.png
docs/_build/html/_static/up-pressed.png
docs/_build/html/_static/up.png
docs/idpflex/bayes.rst
docs/idpflex/cluster.rst
docs/idpflex/cnextend.rst
docs/idpflex/distances.rst
docs/idpflex/properties.rst
docs/idpflex/utils.rst
docs/images/data_download_ascii_file.png
docs/images/data_download_file.png
docs/images/data_download_zip.png
docs/images/gitter_logo.png
docs/images/with_python.png
idpflex/__init__.py
idpflex/bayes.py
idpflex/cluster.py
idpflex/cnextend.py
idpflex/distances.py
idpflex/properties.py
idpflex/utils.py
idpflex.egg-info/PKG-INFO
idpflex.egg-info/SOURCES.txt
idpflex.egg-info/dependency_links.txt
idpflex.egg-info/not-zip-safe
idpflex.egg-info/requires.txt
idpflex.egg-info/top_level.txt
tests/__init__.py
tests/conftest.py
tests/test_bayes.py
tests/test_cluster.py
tests/test_cnextend.py
tests/test_distances.py
tests/test_integration.py
tests/test_properties.py
tests/test_utils.py
tests/data/agglomeration.history
tests/data/linkage_matrix
tests/data/sans/profiles.h5
tests/data/saxs/crysol.dat
tests/data/simulation/.hiAPP.xtc_offsets.npz
tests/data/simulation/hiAPP.dssp
tests/data/simulation/hiAPP.pdb
tests/data/simulation/hiAPP.xtc