Metadata-Version: 1.1
Name: idpflex
Version: 0.1.7
Summary: UNKNOWN
Home-page: https://github.com/jmborr/idpflex
Author: Jose Borreguero
Author-email: borreguero@gmail.com
License: MIT license
Keywords: idpflex
Platform: UNKNOWN
Classifier: Development Status :: 5 - Production/Stable
Classifier: Intended Audience :: Science/Research
Classifier: Topic :: Scientific/Engineering :: Physics
Classifier: License :: OSI Approved :: MIT License
Classifier: Natural Language :: English
Classifier: Programming Language :: Python :: 2.7
Classifier: Programming Language :: Python :: 3
Classifier: Programming Language :: Python :: 3.3
Classifier: Programming Language :: Python :: 3.4
Classifier: Programming Language :: Python :: 3.5
